Metadata-Version: 2.1
Name: asynccasbin
Version: 1.1.8
Summary: An async authorization library that supports access control models like ACL, RBAC, ABAC in Python
Home-page: https://github.com/chapagainmanoj/pycasbin
Author: Manoj Chapagain
Author-email: chapagainmanoj35@gmail.com
License: Apache 2.0
Keywords: casbin,acl,rbac,abac,auth,authz,authorization,access control,permission
Platform: UNKNOWN
Classifier: Programming Language :: Python :: 3.3
Classifier: Programming Language :: Python :: 3.4
Classifier: Programming Language :: Python :: 3.5
Classifier: Programming Language :: Python :: 3.6
Classifier: Programming Language :: Python :: 3.7
Classifier: Programming Language :: Python :: 3.8
Classifier: License :: OSI Approved :: Apache Software License
Classifier: Operating System :: OS Independent
Requires-Python: >=3.7
License-File: LICENSE
Requires-Dist: bracex (==2.1.1)
Requires-Dist: unicode (==2.8)
Requires-Dist: wcmatch (==8.2)
